{
    "1": {
        "0": {
            "X": 2095,
            "A": 2095,
            "B": 1929
        },
        "1": {
            "X": 2038,
            "A": 2046,
            "B": 2038
        },
        "2": {
            "X": 1927,
            "A": 1927,
            "B": 1951
        },
        "3": {
            "X": 1950,
            "A": 1882,
            "B": 1950
        },
        "4": {
            "X": 1965,
            "A": 1965,
            "B": 1888
        },
        "5": {
            "X": 1972,
            "A": 1996,
            "B": 1972
        },
        "6": {
            "X": 2013,
            "A": 2054,
            "B": 2013
        },
        "7": {
            "X": 1876,
            "A": 1876,
            "B": 1930
        }
    },
    "2": {
        "0": {
            "X": 1932,
            "A": 1932,
            "B": 1961
        },
        "1": {
            "X": 1903,
            "A": 1959,
            "B": 1903
        },
        "2": {
            "X": 1995,
            "A": 1876,
            "B": 1995
        },
        "3": {
            "X": 1886,
            "A": 1956,
            "B": 1886
        },
        "4": {
            "X": 2045,
            "A": 2017,
            "B": 2045
        },
        "5": {
            "X": 2090,
            "A": 2090,
            "B": 1993
        },
        "6": {
            "X": 2002,
            "A": 1968,
            "B": 2002
        },
        "7": {
            "X": 2005,
            "A": 2062,
            "B": 2005
        }
    },
    "3": {
        "0": {
            "X": 2019,
            "A": 2053,
            "B": 2019
        },
        "1": {
            "X": 2044,
            "A": 2044,
            "B": 2037
        },
        "2": {
            "X": 2061,
            "A": 2094,
            "B": 2061
        },
        "3": {
            "X": 2082,
            "A": 1945,
            "B": 2082
        },
        "4": {
            "X": 2087,
            "A": 2087,
            "B": 1968
        },
        "5": {
            "X": 2017,
            "A": 2017,
            "B": 1962
        },
        "6": {
            "X": 2096,
            "A": 2044,
            "B": 2096
        },
        "7": {
            "X": 2040,
            "A": 2040,
            "B": 1931
        }
    },
    "4": {
        "0": {
            "X": 1878,
            "A": 1878,
            "B": 1932
        },
        "1": {
            "X": 1947,
            "A": 1916,
            "B": 1947
        },
        "2": {
            "X": 1928,
            "A": 1928,
            "B": 2052
        },
        "3": {
            "X": 2003,
            "A": 2004,
            "B": 2003
        },
        "4": {
            "X": 1959,
            "A": 2064,
            "B": 1959
        },
        "5": {
            "X": 1948,
            "A": 2042,
            "B": 1948
        },
        "6": {
            "X": 1930,
            "A": 1916,
            "B": 1930
        },
        "7": {
            "X": 1996,
            "A": 1937,
            "B": 1996
        }
    },
    "5": {
        "0": {
            "X": 2070,
            "A": 2032,
            "B": 2070
        },
        "1": {
            "X": 2031,
            "A": 1981,
            "B": 2031
        },
        "2": {
            "X": 1993,
            "A": 1968,
            "B": 1993
        },
        "3": {
            "X": 1936,
            "A": 1936,
            "B": 2062
        },
        "4": {
            "X": 1978,
            "A": 1882,
            "B": 1978
        },
        "5": {
            "X": 1880,
            "A": 1880,
            "B": 1959
        },
        "6": {
            "X": 1897,
            "A": 1884,
            "B": 1897
        },
        "7": {
            "X": 1954,
            "A": 1954,
            "B": 2002
        }
    },
    "6": {
        "0": {
            "X": 1987,
            "A": 1987,
            "B": 2064
        },
        "1": {
            "X": 2049,
            "A": 2040,
            "B": 2049
        },
        "2": {
            "X": 1952,
            "A": 1973,
            "B": 1952
        },
        "3": {
            "X": 2093,
            "A": 2093,
            "B": 2051
        },
        "4": {
            "X": 1961,
            "A": 1961,
            "B": 2046
        },
        "5": {
            "X": 2051,
            "A": 2051,
            "B": 1965
        },
        "6": {
            "X": 1949,
            "A": 1898,
            "B": 1949
        },
        "7": {
            "X": 1907,
            "A": 1907,
            "B": 1893
        }
    },
    "7": {
        "0": {
            "X": 1980,
            "A": 1980,
            "B": 1930
        },
        "1": {
            "X": 2026,
            "A": 2026,
            "B": 1963
        },
        "2": {
            "X": 1956,
            "A": 1956,
            "B": 1927
        },
        "3": {
            "X": 2029,
            "A": 2088,
            "B": 2029
        },
        "4": {
            "X": 1957,
            "A": 1968,
            "B": 1957
        },
        "5": {
            "X": 1881,
            "A": 1956,
            "B": 1881
        },
        "6": {
            "X": 1989,
            "A": 1936,
            "B": 1989
        },
        "7": {
            "X": 2007,
            "A": 2007,
            "B": 1996
        }
    }
}